Snape.py
Snape-1.0.dist-info/METADATA
Snape-1.0.dist-info/RECORD
Snape-1.0.dist-info/WHEEL
Snape-1.0.dist-info/entry_points.txt
Snape-1.0.dist-info/top_level.txt
