Metadata-Version: 2.1
Name: Snape
Version: 1.0
Summary: Minimalism snippet manager
Home-page: https://github.com/xiaket/Snape
Author: Kai Xia
Author-email: xiaket@gmail.com
License: UNKNOWN
Keywords: snippet manager,snippets
Platform: UNKNOWN
Classifier: Development Status :: 4 - Beta
Classifier: Intended Audience :: Developers
Classifier: License :: OSI Approved :: MIT License
Classifier: Topic :: Utilities
